openmc_tally_unit_converter/__init__.py
openmc_tally_unit_converter/neutronics_units.txt
openmc_tally_unit_converter/utils.py
openmc_tally_unit_converter-0.3.1.dist-info/LICENSE
openmc_tally_unit_converter-0.3.1.dist-info/METADATA
openmc_tally_unit_converter-0.3.1.dist-info/WHEEL
openmc_tally_unit_converter-0.3.1.dist-info/top_level.txt
openmc_tally_unit_converter-0.3.1.dist-info/RECORD
