Metadata-Version: 2.1
Name: openmc-tally-unit-converter
Version: 0.3.1
Summary: Convert OpenMC tallies into user friendly units
Home-page: https://github.com/fusion-energy/openmc_tally_unit_converter
Author: The openmc tally unit converter Development Team
Author-email: mail@jshimwell.com
License: UNKNOWN
Platform: UNKNOWN
Classifier: Natural Language :: English
Classifier: Topic :: Scientific/Engineering
Classifier: Programming Language :: Python :: 3
Classifier: Programming Language :: Python :: 3.6
Classifier: Programming Language :: Python :: 3.7
Classifier: Programming Language :: Python :: 3.8
Classifier: Programming Language :: Python :: 3.9
Classifier: License :: OSI Approved :: MIT License
Classifier: Operating System :: OS Independent
Requires-Python: >=3.6
License-File: LICENSE
Requires-Dist: pint
